coco_to_yolo/__init__.py
coco_to_yolo/coco_to__yolo.py
coco_to_yolo-1.2.1.dist-info/licenses/LICENSE
coco_to_yolo-1.2.1.dist-info/METADATA
coco_to_yolo-1.2.1.dist-info/WHEEL
coco_to_yolo-1.2.1.dist-info/entry_points.txt
coco_to_yolo-1.2.1.dist-info/top_level.txt
coco_to_yolo-1.2.1.dist-info/RECORD
